Metadata-Version: 2.1
Name: nsfw
Version: 0.3.2
Summary: A Python package for analyzing images using Caffe and Yahoo's open_nsfw models.
Home-page: https://github.com/jgarber623/python-nsfw
Author: Jason Garber
Author-email: jason@sixtwothree.org
License: MIT
Platform: any
Classifier: Development Status :: 4 - Beta
Classifier: License :: OSI Approved :: MIT License
Classifier: Programming Language :: Python :: 3
Classifier: Topic :: Multimedia :: Graphics
Classifier: Topic :: Scientific/Engineering :: Image Recognition
Classifier: Topic :: Utilities
Requires-Python: >=3
